{
    "/assets/js/app.js": "/assets/js/app.js",
    "/assets/js/auth.js": "/assets/js/auth.js",
    "/assets/js/index_page.js": "/assets/js/index_page.js",
    "/assets/js/functions.js": "/assets/js/functions.js",
    "/assets/js/update_data_user.js": "/assets/js/update_data_user.js",
    "/assets/js/search_ticket_page.js": "/assets/js/search_ticket_page.js",
    "/assets/css/my_pofile.css": "/assets/css/my_pofile.css",
    "/assets/css/auth.css": "/assets/css/auth.css",
    "/assets/css/style.css": "/assets/css/style.css",
    "/assets/images/favicon.png": "/assets/images/favicon.png",
    "/assets/images/logo.png": "/assets/images/logo.png",
    "/assets/images/logo_old.png": "/assets/images/logo_old.png"
}
